tensorflow_lattice_gpu-0.9.8.data/purelib/tensorflow_lattice/__init__.py
tensorflow_lattice_gpu-0.9.8.data/purelib/tensorflow_lattice/cc/__init__.py
tensorflow_lattice_gpu-0.9.8.data/purelib/tensorflow_lattice/cc/kernels/BUILD
tensorflow_lattice_gpu-0.9.8.data/purelib/tensorflow_lattice/cc/lib/BUILD
tensorflow_lattice_gpu-0.9.8.data/purelib/tensorflow_lattice/cc/ops/__init__.py
tensorflow_lattice_gpu-0.9.8.data/purelib/tensorflow_lattice/cc/ops/_lattice_ops.so
tensorflow_lattice_gpu-0.9.8.data/purelib/tensorflow_lattice/cc/ops/_pwl_calibration_ops.so
tensorflow_lattice_gpu-0.9.8.data/purelib/tensorflow_lattice/cc/tflite_ops/BUILD
tensorflow_lattice_gpu-0.9.8.data/purelib/tensorflow_lattice/cc/tflite_ops/README.md
tensorflow_lattice_gpu-0.9.8.data/purelib/tensorflow_lattice/cc/tflite_ops/freeze_graph_wrapper.py
tensorflow_lattice_gpu-0.9.8.data/purelib/tensorflow_lattice/cc/tflite_ops/toco_wrapper.py
tensorflow_lattice_gpu-0.9.8.data/purelib/tensorflow_lattice/python/__init__.py
tensorflow_lattice_gpu-0.9.8.data/purelib/tensorflow_lattice/python/estimators/__init__.py
tensorflow_lattice_gpu-0.9.8.data/purelib/tensorflow_lattice/python/estimators/base.py
tensorflow_lattice_gpu-0.9.8.data/purelib/tensorflow_lattice/python/estimators/calibrated.py
tensorflow_lattice_gpu-0.9.8.data/purelib/tensorflow_lattice/python/estimators/calibrated_etl.py
tensorflow_lattice_gpu-0.9.8.data/purelib/tensorflow_lattice/python/estimators/calibrated_lattice.py
tensorflow_lattice_gpu-0.9.8.data/purelib/tensorflow_lattice/python/estimators/calibrated_linear.py
tensorflow_lattice_gpu-0.9.8.data/purelib/tensorflow_lattice/python/estimators/calibrated_rtl.py
tensorflow_lattice_gpu-0.9.8.data/purelib/tensorflow_lattice/python/estimators/hparams.py
tensorflow_lattice_gpu-0.9.8.data/purelib/tensorflow_lattice/python/estimators/separately_calibrated_rtl.py
tensorflow_lattice_gpu-0.9.8.data/purelib/tensorflow_lattice/python/lib/__init__.py
tensorflow_lattice_gpu-0.9.8.dist-info/LICENSE
tensorflow_lattice_gpu-0.9.8.dist-info/METADATA
tensorflow_lattice_gpu-0.9.8.dist-info/WHEEL
tensorflow_lattice_gpu-0.9.8.dist-info/entry_points.txt
tensorflow_lattice_gpu-0.9.8.dist-info/top_level.txt
tensorflow_lattice_gpu-0.9.8.dist-info/RECORD
