Metadata-Version: 2.1
Name: tensorflow-lattice-gpu
Version: 0.9.8
Summary: TensorFlow Lattice provides lattice models in TensorFlow
Home-page: https://github.com/tensorflow/lattice
Author: Google Inc.
Author-email: tensorflow-lattice-releasing@google.com
License: Apache 2.0
Keywords: lattice tensorflow tensor machine learning
Platform: UNKNOWN
Classifier: Development Status :: 4 - Beta
Classifier: Intended Audience :: Developers
Classifier: Intended Audience :: Education
Classifier: Intended Audience :: Science/Research
Classifier: License :: OSI Approved :: Apache Software License
Classifier: Programming Language :: Python :: 2.7
Classifier: Programming Language :: Python :: 3.4
Classifier: Programming Language :: Python :: 3.5
Classifier: Programming Language :: Python :: 3.6
Classifier: Topic :: Scientific/Engineering :: Mathematics
Classifier: Topic :: Software Development :: Libraries :: Python Modules
Classifier: Topic :: Software Development :: Libraries
Requires-Dist: six (>=1.11.0)
Requires-Dist: protobuf (>=3.6.0)
Requires-Dist: numpy (>=1.14.0)
Requires-Dist: tensorflow-gpu (==1.11.0)
